abzagent/__init__.py
abzagent/agent.py
abzagent-0.3.0.dist-info/METADATA
abzagent-0.3.0.dist-info/WHEEL
abzagent-0.3.0.dist-info/top_level.txt
abzagent-0.3.0.dist-info/RECORD
