Metadata-Version: 2.4
Name: abzagent
Version: 0.3.0
Summary: The Fastest Way to build AI Agent Using Gemini.
Author: Abu Bakar
Author-email: abubakarbinzohaib@gmail.com
Requires-Dist: google-generativeai
Requires-Dist: python-dotenv
Dynamic: author
Dynamic: author-email
Dynamic: description
Dynamic: description-content-type
Dynamic: requires-dist
Dynamic: summary
